ez_hangul/__init__.py
ez_hangul-0.1.4.dist-info/METADATA
ez_hangul-0.1.4.dist-info/WHEEL
ez_hangul-0.1.4.dist-info/top_level.txt
ez_hangul-0.1.4.dist-info/RECORD
