Metadata-Version: 2.4
Name: ez-hangul
Version: 0.1.4
Summary: 한글 자모 분리, 조합, 조사 자동 처리 유틸리티
Home-page: https://github.com/newhajinyoon/ez-hangul
Author: Jinyoon
Author-email: jinyoonbz@gmail.com
Classifier: Programming Language :: Python :: 3
Classifier: Operating System :: OS Independent
Classifier: Topic :: Text Processing :: Linguistic
Classifier: Natural Language :: Korean
Requires-Python: >=3.6
Dynamic: author
Dynamic: author-email
Dynamic: classifier
Dynamic: description
Dynamic: description-content-type
Dynamic: home-page
Dynamic: requires-python
Dynamic: summary
